bluer_sbc/__init__.py
bluer_sbc/__main__.py
bluer_sbc/config.env
bluer_sbc/env.py
bluer_sbc/host.py
bluer_sbc/logger.py
bluer_sbc/sample.env
bluer_sbc/urls.py
bluer_sbc/.abcli/abcli.sh
bluer_sbc/.abcli/actions.sh
bluer_sbc/.abcli/adafruit_rgb_matrix.sh
bluer_sbc/.abcli/alias.sh
bluer_sbc/.abcli/bluer_sbc.sh
bluer_sbc/.abcli/camera.sh
bluer_sbc/.abcli/grove.sh
bluer_sbc/.abcli/hat.sh
bluer_sbc/.abcli/lepton.sh
bluer_sbc/.abcli/rpi.sh
bluer_sbc/.abcli/scroll_phat_hd.sh
bluer_sbc/.abcli/seed.sh
bluer_sbc/.abcli/session.sh
bluer_sbc/.abcli/sparkfun_top_phat.sh
bluer_sbc/.abcli/unicorn_16x16.sh
bluer_sbc/.abcli/install/90deg_screen.sh
bluer_sbc/.abcli/install/adafruit_rgb_matrix.sh
bluer_sbc/.abcli/install/grove.sh
bluer_sbc/.abcli/install/lepton.sh
bluer_sbc/.abcli/install/scroll_phat_hd.sh
bluer_sbc/.abcli/install/sparkfun_top_phat.sh
bluer_sbc/.abcli/install/template.sh
bluer_sbc/.abcli/install/unicorn_16x16.sh
bluer_sbc/.abcli/rpi/fake_display.sh
bluer_sbc/.abcli/sbc/parts.sh
bluer_sbc/.abcli/sbc/parts/adjust.sh
bluer_sbc/.abcli/sbc/parts/cd.sh
bluer_sbc/.abcli/sbc/parts/edit.sh
bluer_sbc/.abcli/sbc/parts/open.sh
bluer_sbc/.abcli/seed/headless_rpi.sh
bluer_sbc/.abcli/seed/headless_rpi_64_bit.sh
bluer_sbc/.abcli/seed/headless_ubuntu_rpi.sh
bluer_sbc/.abcli/seed/jetson.sh
bluer_sbc/.abcli/seed/rpi.sh
bluer_sbc/.abcli/seed/rpi_64_bit.sh
bluer_sbc/.abcli/seed/swallow_raspbian.sh
bluer_sbc/.abcli/tests/README.sh
bluer_sbc/.abcli/tests/camera.sh
bluer_sbc/.abcli/tests/help.sh
bluer_sbc/.abcli/tests/parts_adjust.sh
bluer_sbc/.abcli/tests/seed.sh
bluer_sbc/.abcli/tests/version.sh
bluer_sbc/README/__init__.py
bluer_sbc/README/aliases.py
bluer_sbc/README/build.py
bluer_sbc/README/design.py
bluer_sbc/README/parts.py
bluer_sbc/README/root.py
bluer_sbc/README/shortcuts.py
bluer_sbc/README/designs/__init__.py
bluer_sbc/README/designs/adapter_bus.py
bluer_sbc/README/designs/blue_bracket.py
bluer_sbc/README/designs/consts.py
bluer_sbc/README/designs/nafha.py
bluer_sbc-9.457.1.dist-info/licenses/LICENSE
bluer_sbc-9.457.1.dist-info/METADATA
bluer_sbc-9.457.1.dist-info/WHEEL
bluer_sbc-9.457.1.dist-info/top_level.txt
bluer_sbc-9.457.1.dist-info/RECORD
