Metadata-Version: 2.4
Name: bluer_sbc
Version: 9.457.1
Summary: 🌀 AI for single board computers and related designs.
Home-page: https://github.com/kamangir/bluer-sbc
Author: Arash Abadpour (Kamangir)
Author-email: arash.abadpour@gmail.com
License: CC0-1.0
Classifier: Programming Language :: Python :: 3
Classifier: Programming Language :: Unix Shell
Classifier: Operating System :: OS Independent
License-File: LICENSE
Requires-Dist: bluer_ai
Dynamic: author
Dynamic: author-email
Dynamic: classifier
Dynamic: description
Dynamic: description-content-type
Dynamic: home-page
Dynamic: license
Dynamic: license-file
Dynamic: requires-dist
Dynamic: summary
